clinlog/Logger.py
clinlog/__init__.py
clinlog/helper.py
clinlog/logging/__init__.py
clinlog/logging/clinlog_handler.py
clinlog/logging/helper.py
clinlog-1.0.0.dist-info/LICENSE
clinlog-1.0.0.dist-info/METADATA
clinlog-1.0.0.dist-info/WHEEL
clinlog-1.0.0.dist-info/top_level.txt
clinlog-1.0.0.dist-info/RECORD
