Metadata-Version: 2.1
Name: clinlog
Version: 1.0.0
Summary: Package to log styled messages on console
Home-page: https://github.com/salpreh/clinlog
Author: salpreh
Author-email: salva.perez46@gmail.com
License: MIT License
Platform: UNKNOWN
License-File: LICENSE
Requires-Dist: colorama (>=0.3.8)
